{
  "tag": "gemma4_e4b",
  "n": 36,
  "accuracy": 0.6944,
  "local_hit_rate_pct": 97.2,
  "remote_tokens": 317,
  "per_category": {
    "classification": {
      "correct": 5,
      "total": 6,
      "acc": 0.833
    },
    "extraction": {
      "correct": 5,
      "total": 6,
      "acc": 0.833
    },
    "math": {
      "correct": 8,
      "total": 8,
      "acc": 1.0
    },
    "qa": {
      "correct": 5,
      "total": 6,
      "acc": 0.833
    },
    "reasoning": {
      "correct": 2,
      "total": 6,
      "acc": 0.333
    },
    "summarization": {
      "correct": 0,
      "total": 4,
      "acc": 0.0
    }
  }
}